craftlet/main.py
craftlet/cli/CraftLetCLI.py
craftlet/features/CraftLet.py
craftlet/features/CraftLetCache.py
craftlet/models/Cacheable.py
craftlet/utils/exceptions.py
craftlet/utils/hashUtils.py
craftlet/utils/helperFunctions.py
craftlet/utils/mappers.py
craftlet-0.2.0.dist-info/METADATA
craftlet-0.2.0.dist-info/WHEEL
craftlet-0.2.0.dist-info/entry_points.txt
craftlet-0.2.0.dist-info/top_level.txt
craftlet-0.2.0.dist-info/RECORD
