Metadata-Version: 2.4
Name: craftlet
Version: 0.2.0
Summary: Add your description here
Requires-Python: >=3.12
Requires-Dist: cbor2>=5.7.1
Requires-Dist: httpx>=0.28.1
Requires-Dist: typer>=0.20.0
